{"nodes":[{"id":"utils_formatting_spec","label":"formatting.spec.ts","file_type":"code","source_file":"src/utils/formatting.spec.ts","source_location":"L1"}],"edges":[{"source":"utils_formatting_spec","target":"vitest","relation":"imports_from","confidence":"EXTRACTED","source_file":"src/utils/formatting.spec.ts","source_location":"L1","weight":1},{"source":"utils_formatting_spec","target":"users_cristianasollini_documents_work_git_avocato_src_utils_formatting_ts","relation":"imports_from","confidence":"EXTRACTED","source_file":"src/utils/formatting.spec.ts","source_location":"L2","weight":1},{"source":"utils_formatting_spec","target":"utils_formatting_formatdatees","relation":"imports","confidence":"EXTRACTED","source_file":"src/utils/formatting.spec.ts","source_location":"L2","weight":1},{"source":"utils_formatting_spec","target":"utils_formatting_formatcalorieentry","relation":"imports","confidence":"EXTRACTED","source_file":"src/utils/formatting.spec.ts","source_location":"L2","weight":1}]}