{"nodes":[{"id":"views_dashboardview","label":"DashboardView.vue","file_type":"code","source_file":"src/views/DashboardView.vue","source_location":"L1"},{"id":"views_dashboardview_confirmdeleteentry","label":"confirmDeleteEntry()","file_type":"code","source_file":"src/views/DashboardView.vue","source_location":"L48"},{"id":"views_dashboardview_executedeleteentry","label":"executeDeleteEntry()","file_type":"code","source_file":"src/views/DashboardView.vue","source_location":"L53"},{"id":"views_dashboardview_canceldeleteentry","label":"cancelDeleteEntry()","file_type":"code","source_file":"src/views/DashboardView.vue","source_location":"L62"},{"id":"views_dashboardview_executecleartoday","label":"executeClearToday()","file_type":"code","source_file":"src/views/DashboardView.vue","source_location":"L67"},{"id":"views_dashboardview_togglemealtype","label":"toggleMealType()","file_type":"code","source_file":"src/views/DashboardView.vue","source_location":"L73"},{"id":"views_dashboardview_mealtypetotalcalories","label":"mealTypeTotalCalories()","file_type":"code","source_file":"src/views/DashboardView.vue","source_location":"L81"},{"id":"views_dashboardview_entrymacros","label":"entryMacros()","file_type":"code","source_file":"src/views/DashboardView.vue","source_location":"L85"},{"id":"views_dashboardview_openplatemodal","label":"openPlateModal()","file_type":"code","source_file":"src/views/DashboardView.vue","source_location":"L97"},{"id":"views_dashboardview_openrecipemodal","label":"openRecipeModal()","file_type":"code","source_file":"src/views/DashboardView.vue","source_location":"L102"},{"id":"views_dashboardview_deleteplate","label":"deletePlate()","file_type":"code","source_file":"src/views/DashboardView.vue","source_location":"L107"},{"id":"views_dashboardview_deleterecipe","label":"deleteRecipe()","file_type":"code","source_file":"src/views/DashboardView.vue","source_location":"L114"}],"edges":[{"source":"views_dashboardview","target":"views_dashboardview_confirmdeleteentry","relation":"contains","confidence":"EXTRACTED","source_file":"src/views/DashboardView.vue","source_location":"L48","weight":1},{"source":"views_dashboardview","target":"views_dashboardview_executedeleteentry","relation":"contains","confidence":"EXTRACTED","source_file":"src/views/DashboardView.vue","source_location":"L53","weight":1},{"source":"views_dashboardview","target":"views_dashboardview_canceldeleteentry","relation":"contains","confidence":"EXTRACTED","source_file":"src/views/DashboardView.vue","source_location":"L62","weight":1},{"source":"views_dashboardview","target":"views_dashboardview_executecleartoday","relation":"contains","confidence":"EXTRACTED","source_file":"src/views/DashboardView.vue","source_location":"L67","weight":1},{"source":"views_dashboardview","target":"views_dashboardview_togglemealtype","relation":"contains","confidence":"EXTRACTED","source_file":"src/views/DashboardView.vue","source_location":"L73","weight":1},{"source":"views_dashboardview","target":"views_dashboardview_mealtypetotalcalories","relation":"contains","confidence":"EXTRACTED","source_file":"src/views/DashboardView.vue","source_location":"L81","weight":1},{"source":"views_dashboardview","target":"views_dashboardview_entrymacros","relation":"contains","confidence":"EXTRACTED","source_file":"src/views/DashboardView.vue","source_location":"L85","weight":1},{"source":"views_dashboardview","target":"views_dashboardview_openplatemodal","relation":"contains","confidence":"EXTRACTED","source_file":"src/views/DashboardView.vue","source_location":"L97","weight":1},{"source":"views_dashboardview","target":"views_dashboardview_openrecipemodal","relation":"contains","confidence":"EXTRACTED","source_file":"src/views/DashboardView.vue","source_location":"L102","weight":1},{"source":"views_dashboardview","target":"views_dashboardview_deleteplate","relation":"contains","confidence":"EXTRACTED","source_file":"src/views/DashboardView.vue","source_location":"L107","weight":1},{"source":"views_dashboardview","target":"views_dashboardview_deleterecipe","relation":"contains","confidence":"EXTRACTED","source_file":"src/views/DashboardView.vue","source_location":"L114","weight":1},{"source":"views_dashboardview","target":"views_dashboardview_confirmdeleteentry","relation":"contains","confidence":"EXTRACTED","source_file":"src/views/DashboardView.vue","source_location":"L47","weight":1},{"source":"views_dashboardview","target":"views_dashboardview_executedeleteentry","relation":"contains","confidence":"EXTRACTED","source_file":"src/views/DashboardView.vue","source_location":"L52","weight":1},{"source":"views_dashboardview","target":"views_dashboardview_canceldeleteentry","relation":"contains","confidence":"EXTRACTED","source_file":"src/views/DashboardView.vue","source_location":"L61","weight":1},{"source":"views_dashboardview","target":"views_dashboardview_executecleartoday","relation":"contains","confidence":"EXTRACTED","source_file":"src/views/DashboardView.vue","source_location":"L66","weight":1},{"source":"views_dashboardview","target":"views_dashboardview_togglemealtype","relation":"contains","confidence":"EXTRACTED","source_file":"src/views/DashboardView.vue","source_location":"L72","weight":1},{"source":"views_dashboardview","target":"views_dashboardview_mealtypetotalcalories","relation":"contains","confidence":"EXTRACTED","source_file":"src/views/DashboardView.vue","source_location":"L80","weight":1},{"source":"views_dashboardview","target":"views_dashboardview_entrymacros","relation":"contains","confidence":"EXTRACTED","source_file":"src/views/DashboardView.vue","source_location":"L84","weight":1},{"source":"views_dashboardview","target":"views_dashboardview_openplatemodal","relation":"contains","confidence":"EXTRACTED","source_file":"src/views/DashboardView.vue","source_location":"L96","weight":1},{"source":"views_dashboardview","target":"views_dashboardview_openrecipemodal","relation":"contains","confidence":"EXTRACTED","source_file":"src/views/DashboardView.vue","source_location":"L101","weight":1}]}